.gitattributes
.gitignore
CITATION.cff
CONTRIBUTING.md
GSOC2022.md
LICENSE.txt
README.md
__init__.py
_version.py
pull_request_template.md
pyproject.toml
requirements.txt
scratchpad.ipynb
setup.cfg
setup.py
.github/workflows/publish.yml
demo/ToDo.md
demo/__init__.py
demo/ab_test_demo.py
demo/beta_binom_post_plot.py
figures/empty
gan/README.md
gan/__init__.py
gan/assembler.py
gan/data.py
gan/run.py
gan/assets/dcgan.png
gan/assets/gp_wgan.png
gan/assets/logan.png
gan/assets/sngan.png
gan/assets/wgan.png
gan/configs/dcgan.yaml
gan/configs/gp_wgan.yaml
gan/configs/logan.yaml
gan/configs/sngan.yaml
gan/configs/wgan.yaml
gan/models/base_gan.py
gan/models/dcgan.py
gan/models/gp_wgan.py
gan/models/logan.py
gan/models/sngan.py
gan/models/wgan.py
gan/sampling/dgflow.py
gan/utils/plotting.py
misc/book_readme_md.py
misc/book_supplements_md.py
misc/convert_to_cmyk.py
misc/github_stats.py
misc/test_scripts.py
old/armijo_mnist_demo.py
old/fisherDiscrimVowelDemo.py
old/kmeansYeastDemo.py
old/ngram_char_model.py
old/subspace_lib.py
old/subspace_opt_lib.py
old/subspace_opt_mlp_demo.py
old/subspace_optimize_mlp_mnist_plot_vs_dim.py
old/subspace_sample_mlp_mnist_fixed_dim.py
old/subspace_sgd_mlp_mnist_demo.py
pyprobml/__init__.py
pyprobml/_version.py
pyprobml.egg-info/PKG-INFO
pyprobml.egg-info/SOURCES.txt
pyprobml.egg-info/dependency_links.txt
pyprobml.egg-info/requires.txt
pyprobml.egg-info/top_level.txt
pyprobml/scripts/KLfwdReverseMixGauss.py
pyprobml/scripts/__init__.py
pyprobml/scripts/ab_test_demo.py
pyprobml/scripts/activation_fun_plot.py
pyprobml/scripts/adf_logistic_regression_demo.py
pyprobml/scripts/ae_celeba_lightning.py
pyprobml/scripts/ae_layerwise_fashion_tf.py
pyprobml/scripts/ae_mnist_conv.py
pyprobml/scripts/ae_mnist_mlp.py
pyprobml/scripts/agglomDemo.py
pyprobml/scripts/ais_demo.py
pyprobml/scripts/anscombes_quartet.py
pyprobml/scripts/antithetic_sampling.py
pyprobml/scripts/ard_classification_demo.py
pyprobml/scripts/ard_linreg_logreg.py
pyprobml/scripts/ard_vb_linreg_logreg.py
pyprobml/scripts/armijo_sgd.py
pyprobml/scripts/ars_demo.py
pyprobml/scripts/ars_envelope.py
pyprobml/scripts/asia_pgm.py
