Metadata-Version: 2.1
Name: pyprobml
Version: 0.0.2
Summary: example description
Home-page: https://github.com/patel-zeel/pyprobml
Author: Kevin Murphy
Author-email: murphyk@gmail.com
License: MIT
Platform: UNKNOWN
Requires-Python: >=3.6
License-File: LICENSE.txt
